{
    "records": [
        {
            "attributes": {
                "type": "Lead",
                "referenceId": "LeadHankPym"
            },
            "Salutation": "Mr.",
            "FirstName": "Hank",
            "LastName": "Pym",
            "Title": "Head of BD&L",
            "Company": "AstraZeneca",
            "BDL_Deal_Type__c": "M&A",
            "Status": "Open",
            "BDL_Has_Budget__c": true,
            "BDL_Decision_Maker__c": true,
            "BDL_Therapeutic_Area__c": "Cardiovascular",
            "BDL_Development_Phase__c": "Phase II",
            "LeadSource": "Partner",
            "BDL_Indications__c": "Alzheimer's Disease;Cardioprotective mechanisms;Diabetic Kidney Disease",
            "BDL_DOI__c": "s00115-021-01222-w",
            "BDL_Clinical_Trials__c": "https://clinicaltrials.gov/ct2/show/NCT03991988?cond=alzheimer&draw=2&rank=1",
            "BDL_PubMed__c": "https://www.ncbi.nlm.nih.gov/pmc/articles/PMC8648638/",
            "Phone": "030882819",
            "Email": "drpym@example.com",
            "MobilePhone": "01734432718",
            "Website": null,
            "Description": "Worked with Dr. Pym a few years back. Very numbers driven and very interested in Cell & Gene Therapy."
        },
         {
            "attributes": {
                "type": "Lead",
                "referenceId": "LeadFerryBouman"
            },
            "Salutation": "Mr.",
            "FirstName": "Ferry",
            "LastName": "Bouman",
            "Title": "Head of M&A",
            "Company": "Novartis",
            "BDL_Deal_Type__c": "M&A",
            "Status": "Open",
            "BDL_Has_Budget__c": true,
            "BDL_Decision_Maker__c": true,
            "BDL_Therapeutic_Area__c": "Cardiovascular",
            "BDL_Development_Phase__c": "Phase I",
            "LeadSource": "Web",
            "BDL_Indications__c": "Alzheimer's Disease",
            "BDL_DOI__c": "s00115-021-01222-w",
            "BDL_Clinical_Trials__c": "https://clinicaltrials.gov/ct2/show/NCT03991988?cond=alzheimer&draw=2&rank=1",
            "BDL_PubMed__c": "https://www.ncbi.nlm.nih.gov/pmc/articles/PMC8648638/",
            "Phone": "030882819",
            "Email": "fbouman@example.com",
            "MobilePhone": "01734432718",
            "Website": null,
            "Description": "Worked with Ferry at Novartis in the best. Setting up strategic Portfolio for C&GT at the moment."
        }
    ]
}